auto_claude/__init__.py
auto_claude/auto_claude.py
auto_claude/inject.js
auto_claude-0.1.4.dist-info/licenses/LICENSE
auto_claude-0.1.4.dist-info/METADATA
auto_claude-0.1.4.dist-info/WHEEL
auto_claude-0.1.4.dist-info/entry_points.txt
auto_claude-0.1.4.dist-info/top_level.txt
auto_claude-0.1.4.dist-info/RECORD
