Metadata-Version: 2.4
Name: auto-claude
Version: 0.1.4
Summary: auto-claude: A CLI tool that injects an auto-approve feature into the Claude Desktop App.
Author: shaneholloman
License: MIT
Project-URL: Homepage, https://github.com/shaneholloman/auto-claude
Project-URL: Repository, https://github.com/shaneholloman/auto-claude
Project-URL: Issues, https://github.com/shaneholloman/auto-claude/issues
Classifier: Programming Language :: Python :: 3
Classifier: License :: OSI Approved :: MIT License
Classifier: Operating System :: OS Independent
Requires-Python: >=3.11
License-File: LICENSE
Requires-Dist: pytest
Requires-Dist: requests
Requires-Dist: websockets
Requires-Dist: ruff
Requires-Dist: mypy
Requires-Dist: types-requests
Dynamic: license-file
